element_animal/__init__.py
element_animal/genotyping.py
element_animal/subject.py
element_animal/surgery.py
element_animal/version.py
element_animal/export/__init__.py
element_animal/export/nwb.py
element_animal-0.1.8.dist-info/LICENSE
element_animal-0.1.8.dist-info/METADATA
element_animal-0.1.8.dist-info/WHEEL
element_animal-0.1.8.dist-info/top_level.txt
element_animal-0.1.8.dist-info/RECORD
