Metadata-Version: 2.1
Name: element-animal
Version: 0.1.8
Summary: DataJoint Element for Animal Management
Home-page: https://github.com/datajoint/element-animal
Author: DataJoint
Author-email: info@datajoint.com
License: MIT
Keywords: neuroscience animal-management datajoint
Platform: UNKNOWN
License-File: LICENSE
Requires-Dist: datajoint (>=0.13)
Requires-Dist: pynwb (>=1.4.0)
